bitcoinutils/__init__.py
bitcoinutils/bech32.py
bitcoinutils/block.py
bitcoinutils/constants.py
bitcoinutils/hdwallet.py
bitcoinutils/keys.py
bitcoinutils/proxy.py
bitcoinutils/psbt.py
bitcoinutils/ripemd160.py
bitcoinutils/schnorr.py
bitcoinutils/script.py
bitcoinutils/setup.py
bitcoinutils/transactions.py
bitcoinutils/utils.py
bitcoin_utils-0.7.3.dist-info/LICENSE
bitcoin_utils-0.7.3.dist-info/METADATA
bitcoin_utils-0.7.3.dist-info/WHEEL
bitcoin_utils-0.7.3.dist-info/top_level.txt
bitcoin_utils-0.7.3.dist-info/RECORD
