Metadata-Version: 2.1
Name: bitcoin-utils
Version: 0.7.3
Summary: Bitcoin utility functions
Home-page: https://github.com/karask/python-bitcoin-utils
Author: Konstantinos Karasavvas
Author-email: kkarasavvas@gmail.com
License: MIT
Keywords: bitcoin library utilities tools
Platform: UNKNOWN
License-File: LICENSE
Requires-Dist: base58check<2.0,>=1.0.2
Requires-Dist: ecdsa<0.20,>=0.19.1
Requires-Dist: hdwallet~=3.0
Requires-Dist: python-bitcoinrpc<2.0,>=1.0
Requires-Dist: sympy<2.0,>=1.2
